comberload.py
comberload-1.1.3.dist-info/LICENSE
comberload-1.1.3.dist-info/METADATA
comberload-1.1.3.dist-info/WHEEL
comberload-1.1.3.dist-info/top_level.txt
comberload-1.1.3.dist-info/RECORD
