Metadata-Version: 2.1
Name: comberload
Version: 1.1.3
Summary: Stop letting heavy packages block down your scripts!
Home-page: https://github.com/ken-morel/comberload
Author: ken-morel
Author-email: engonken8@gmail.com
Maintainer: ken-morel
Maintainer-email: engonken8@gmail.com
License: MIT
Project-URL: Funding, https://ko-fi.com/kenmorel
Project-URL: Source, https://github.com/ken-morel/comberload/
Project-URL: Tracker, https://github.com/ken-morel/comberload/issues
Classifier: Intended Audience :: Developers
Classifier: Development Status :: 3 - Alpha
Classifier: License :: OSI Approved :: MIT License
Classifier: Programming Language :: Python
Classifier: Programming Language :: Python :: 3
Classifier: Programming Language :: Python :: 3.10
Classifier: Programming Language :: Python :: 3.11
Classifier: Programming Language :: Python :: 3.12
Classifier: Natural Language :: English
Classifier: Topic :: Software Development :: Libraries :: Python Modules
License-File: LICENSE
Provides-Extra: dev
Requires-Dist: pytest; extra == "dev"
Requires-Dist: pytest-cov; extra == "dev"
Provides-Extra: ci
Requires-Dist: pytest; extra == "ci"
Requires-Dist: pytest-cov; extra == "ci"
Requires-Dist: coveralls; extra == "ci"
